{
    "key": "group_5684377c7b7c7",
    "title": "Options: Theme",
    "fields": [
        {
            "key": "field_5694079bf7a0e",
            "label": "Featured Content",
            "name": "",
            "type": "tab",
            "instructions": "",
            "required": 0,
            "conditional_logic": 0,
            "wrapper": {
                "width": "",
                "class": "",
                "id": ""
            },
            "placement": "top",
            "endpoint": 0
        },
        {
            "key": "field_568307b6e3c41abe",
            "label": "Most Popular Sidebar Header Image",
            "name": "most_popular_image",
            "type": "image",
            "instructions": "Image to appear behind the title in the sidebar. Recommended minimum size: 600px x 400px",
            "required": 0,
            "conditional_logic": 0,
            "wrapper": {
                "width": "",
                "class": "",
                "id": ""
            },
            "return_format": "array",
            "preview_size": "thumbnail",
            "library": "all",
            "min_width": "",
            "min_height": "",
            "min_size": "",
            "max_width": "",
            "max_height": "",
            "max_size": "",
            "mime_types": ""
        },
        {
            "key": "field_fas9f87e0q2asf",
            "label": "Default Collection",
            "name": "collection",
            "type": "post_object",
            "instructions": "Default collection appearing at the bottom of articles when no collection is selected for that post. Add a collection under <a href=\"\/wp-admin\/edit.php?post_type=collections\">collections<\/a>",
            "required": 0,
            "conditional_logic": 0,
            "wrapper": {
                "width": "",
                "class": "",
                "id": ""
            },
            "post_type": [
                "collections"
            ],
            "taxonomy": "",
            "allow_null": 0,
            "multiple": 0,
            "return_format": "object",
            "ui": 1
        },
        {
            "key": "field_5f104c4fbf9e7",
            "label": "Trending Articles",
            "name": "",
            "type": "tab",
            "instructions": "",
            "required": 0,
            "conditional_logic": 0,
            "wrapper": {
                "width": "",
                "class": "",
                "id": ""
            },
            "placement": "top",
            "endpoint": 0
        },
        {
            "key": "field_5f104c80bf9e8",
            "label": "Global module title",
            "name": "trending_articles_title_global",
            "type": "text",
            "instructions": "",
            "required": 0,
            "conditional_logic": 0,
            "wrapper": {
                "width": "",
                "class": "",
                "id": ""
            },
            "default_value": "",
            "placeholder": "",
            "prepend": "",
            "append": "",
            "maxlength": ""
        },
        {
            "key": "field_5f104ccfbf9e9",
            "label": "Fetch trending posts from Parse.ly or fetch latest from WordPress?",
            "name": "trending_articles_fetch_parsely_global",
            "type": "true_false",
            "instructions": "",
            "required": 0,
            "conditional_logic": 0,
            "wrapper": {
                "width": "",
                "class": "",
                "id": ""
            },
            "message": "",
            "default_value": 1,
            "ui": 1,
            "ui_on_text": "Trending from Parse.ly",
            "ui_off_text": "Latest from WordPress"
        },
        {
            "key": "field_sa07babcqw4",
            "label": "Related Content",
            "name": "",
            "type": "tab",
            "instructions": "",
            "required": 0,
            "conditional_logic": 0,
            "wrapper": {
                "width": "",
                "class": "",
                "id": ""
            },
            "placement": "top",
            "endpoint": 0
        },
        {
            "key": "field_5f0c8700c377f",
            "label": "Show on posts",
            "name": "show_related_content",
            "type": "true_false",
            "instructions": "",
            "required": 0,
            "conditional_logic": 0,
            "wrapper": {
                "width": "",
                "class": "",
                "id": ""
            },
            "message": "",
            "default_value": 1,
            "ui": 1,
            "ui_on_text": "Show",
            "ui_off_text": "Hide"
        },
        {
            "key": "field_5f0c86f2c377e",
            "label": "Global Elements",
            "name": "",
            "type": "tab",
            "instructions": "",
            "required": 0,
            "conditional_logic": 0,
            "wrapper": {
                "width": "",
                "class": "",
                "id": ""
            },
            "placement": "top",
            "endpoint": 0
        },
        {
            "key": "field_56843dd4fbdc1",
            "label": "Logo Graphic",
            "name": "logo_graphic",
            "type": "image",
            "instructions": "Recommended minimum size: 300px x 300px",
            "required": 0,
            "conditional_logic": 0,
            "wrapper": {
                "width": "",
                "class": "",
                "id": ""
            },
            "return_format": "array",
            "preview_size": "thumbnail",
            "library": "all",
            "min_width": "",
            "min_height": "",
            "min_size": "",
            "max_width": "",
            "max_height": "",
            "max_size": "",
            "mime_types": ""
        },
        {
            "key": "field_56c5df08769f1",
            "label": "Main Menu Category Sub Nav",
            "name": "main_menu_category_sub_nav",
            "type": "repeater",
            "instructions": "",
            "required": 0,
            "conditional_logic": 0,
            "wrapper": {
                "width": "",
                "class": "",
                "id": ""
            },
            "collapsed": "",
            "min": 0,
            "max": 0,
            "layout": "row",
            "button_label": "Add Category",
            "sub_fields": [
                {
                    "key": "field_56c738c01e6b9",
                    "label": "Category",
                    "name": "category",
                    "type": "taxonomy",
                    "instructions": "Choose the category to show 4 most recent posts",
                    "required": 0,
                    "conditional_logic": 0,
                    "wrapper": {
                        "width": "",
                        "class": "",
                        "id": ""
                    },
                    "taxonomy": "category",
                    "field_type": "select",
                    "allow_null": 0,
                    "add_term": 0,
                    "save_terms": 0,
                    "load_terms": 0,
                    "return_format": "object",
                    "multiple": 0
                },
                {
                    "key": "field_56c5df1e769f2",
                    "label": "Class",
                    "name": "class",
                    "type": "text",
                    "instructions": "Class name must match CSS defined in menu for the associated category",
                    "required": 0,
                    "conditional_logic": 0,
                    "wrapper": {
                        "width": "",
                        "class": "",
                        "id": ""
                    },
                    "default_value": "",
                    "placeholder": "",
                    "prepend": "",
                    "append": "",
                    "maxlength": "",
                    "readonly": 0,
                    "disabled": 0
                },
                {
                    "key": "field_56c5dfdd769f3",
                    "label": "Featured Tags",
                    "name": "main_menu_category_sub_nav_tags",
                    "type": "taxonomy",
                    "instructions": "Tags to feature in this category sub menu (up to 6 allowed)",
                    "required": 0,
                    "conditional_logic": 0,
                    "wrapper": {
                        "width": "",
                        "class": "",
                        "id": ""
                    },
                    "taxonomy": "post_tag",
                    "field_type": "multi_select",
                    "allow_null": 0,
                    "add_term": 0,
                    "save_terms": 0,
                    "load_terms": 0,
                    "return_format": "object",
                    "multiple": 0
                },
                {
                    "key": "field_56c7390f1e6ba",
                    "label": "Featured Post",
                    "name": "featured_post",
                    "type": "relationship",
                    "instructions": "Post to be featured before the 4 most recent",
                    "required": 1,
                    "conditional_logic": 0,
                    "wrapper": {
                        "width": "",
                        "class": "",
                        "id": ""
                    },
                    "post_type": [
                        "post",
                        "page"
                    ],
                    "taxonomy": [],
                    "allow_null": 0,
                    "min": 0,
                    "max": 1,
                    "return_format": "object",
                    "ui": 1,
                    "filters": [
                        "search",
                        "post_type",
                        "taxonomy"
                    ],
                    "elements": []
                },
                {
                    "key": "field_56c5dfdd769f4",
                    "label": "Featured Post Image",
                    "name": "featured_post_image",
                    "type": "image",
                    "instructions": "Uploaded image should have an aspect ratio of 3:2",
                    "required": 0,
                    "conditional_logic": 0,
                    "wrapper": {
                        "width": "",
                        "class": "",
                        "id": ""
                    },
                    "return_format": "array",
                    "preview_size": "thumbnail",
                    "library": "all",
                    "min_width": "",
                    "min_height": "",
                    "min_size": "",
                    "max_width": "",
                    "max_height": "",
                    "max_size": "",
                    "mime_types": ""
                }
            ]
        },
        {
            "key": "field_945213452151",
            "label": "Main Menu Video Sub Nav",
            "name": "",
            "type": "message",
            "instructions": "",
            "required": 0,
            "conditional_logic": 0,
            "wrapper": {
                "width": "",
                "class": "",
                "id": ""
            },
            "_input": "",
            "new_lines": "wpautotop",
            "esc_html": 0,
            "message": ""
        },
        {
            "key": "field_945213452152",
            "label": "Main Menu Featured Video Class",
            "name": "main_menu_video_class",
            "type": "text",
            "instructions": "Class name must match CSS defined in menu for the associated category",
            "required": 0,
            "conditional_logic": 0,
            "wrapper": {
                "width": "",
                "class": "",
                "id": ""
            },
            "_input": "",
            "default_value": "",
            "placeholder": "",
            "prepend": "",
            "append": "",
            "maxlength": "",
            "readonly": 0,
            "disabled": 0
        },
        {
            "key": "field_945213452153",
            "label": "Featured Video Post",
            "name": "featured_video_post",
            "type": "relationship",
            "instructions": "Post to be featured before the 4 most recent",
            "required": 0,
            "conditional_logic": 0,
            "wrapper": {
                "width": "",
                "class": "",
                "id": ""
            },
            "_input": "",
            "post_type": [
                "post",
                "page"
            ],
            "taxonomy": [
                "post_tag:video"
            ],
            "allow_null": 0,
            "min": 0,
            "max": 1,
            "return_format": "object",
            "ui": 1,
            "filters": [
                "search",
                "post_type",
                "taxonomy"
            ],
            "elements": []
        },
        {
            "key": "field_945213452154",
            "label": "Video Sub Menu Navigation",
            "name": "main_menu_video_nav",
            "type": "repeater",
            "instructions": "",
            "required": 0,
            "conditional_logic": 0,
            "wrapper": {
                "width": "",
                "class": "",
                "id": ""
            },
            "_input": "",
            "min": 0,
            "max": 0,
            "layout": "table",
            "button_label": "Add New Link",
            "collapsed": "",
            "sub_fields": [
                {
                    "key": "field_9452134521541",
                    "label": "Nav Text",
                    "name": "nav_text",
                    "type": "text",
                    "instructions": "",
                    "required": 1,
                    "conditional_logic": 0,
                    "wrapper": {
                        "width": "",
                        "class": "",
                        "id": ""
                    },
                    "_input": "",
                    "default_value": "",
                    "placeholder": "",
                    "prepend": "",
                    "append": "",
                    "maxlength": 100,
                    "readonly": 0,
                    "disabled": 0
                },
                {
                    "key": "field_9452134521542",
                    "label": "Nav Link",
                    "name": "nav_link",
                    "type": "text",
                    "instructions": "",
                    "required": 1,
                    "conditional_logic": 0,
                    "wrapper": {
                        "width": "",
                        "class": "",
                        "id": ""
                    },
                    "_input": "",
                    "default_value": "",
                    "placeholder": "",
                    "prepend": "",
                    "append": "",
                    "maxlength": 100,
                    "readonly": 0,
                    "disabled": 0
                }
            ]
        },
        {
            "key": "field_5a56f0ab5c3d2",
            "label": "Featured Navigation Title",
            "name": "featured_navigation_title",
            "type": "text",
            "instructions": "Title displayed above the featured navigation link",
            "required": 0,
            "conditional_logic": 0,
            "wrapper": {
                "width": "50",
                "class": "",
                "id": ""
            },
            "default_value": "Featured",
            "placeholder": "",
            "prepend": "",
            "append": "",
            "maxlength": ""
        },
        {
            "key": "field_5a4ffb4cd0f32",
            "label": "Featured Navigation Label",
            "name": "featured_navigation_label",
            "type": "text",
            "instructions": "The label for the featured navigation item in the global nav. ( Limited to 20 characters to maintain design ).",
            "required": 0,
            "conditional_logic": 0,
            "wrapper": {
                "width": "50",
                "class": "",
                "id": ""
            },
            "default_value": "",
            "placeholder": "",
            "prepend": "",
            "append": "",
            "maxlength": 20
        },
        {
            "key": "field_5a4ffb24c8e86",
            "label": "Featured Navigation Link",
            "name": "featured_navigation_link",
            "type": "url",
            "instructions": "The url for the featured link in the navigation system.",
            "required": 0,
            "conditional_logic": 0,
            "wrapper": {
                "width": "40",
                "class": "",
                "id": ""
            },
            "default_value": "",
            "placeholder": ""
        },
        {
            "key": "field_5a56f0705c3d1",
            "label": "Featured Navigation Color",
            "name": "featured_navigation_color",
            "type": "color_picker",
            "instructions": "Color of the featured nav block.",
            "required": 0,
            "conditional_logic": 0,
            "wrapper": {
                "width": "30",
                "class": "",
                "id": ""
            },
            "default_value": "#E06758"
        },
        {
            "key": "field_5afb1c197f2e6",
            "label": "Featured Navigation Image",
            "name": "featured_navigation_image",
            "type": "image",
            "instructions": "Overrides background color on desktop.\r\nRecommended size: 250px by 250px",
            "required": 0,
            "conditional_logic": 0,
            "wrapper": {
                "width": "30",
                "class": "",
                "id": ""
            },
            "return_format": "array",
            "preview_size": "thumbnail",
            "library": "all",
            "min_width": "",
            "min_height": "",
            "min_size": "",
            "max_width": "",
            "max_height": "",
            "max_size": "",
            "mime_types": ""
        },
        {
            "key": "field_9243gascxgae",
            "label": "Featured Image Fallback",
            "name": "featured_image_fallback",
            "type": "image",
            "instructions": "Recommended minimum size: 850px x 560px",
            "required": 0,
            "conditional_logic": 0,
            "wrapper": {
                "width": "",
                "class": "",
                "id": ""
            },
            "return_format": "array",
            "preview_size": "thumbnail",
            "library": "all",
            "min_width": "",
            "min_height": "",
            "min_size": "",
            "max_width": "",
            "max_height": "",
            "max_size": "",
            "mime_types": ""
        },
        {
            "key": "field_5f15f9a0104ea",
            "label": "Spotlight Bar Enabled",
            "name": "spotlight_bar_enabled",
            "type": "true_false",
            "instructions": "",
            "required": 0,
            "conditional_logic": 0,
            "wrapper": {
                "width": "",
                "class": "",
                "id": ""
            },
            "message": "",
            "default_value": 0,
            "ui": 0,
            "ui_on_text": "",
            "ui_off_text": ""
        },
        {
            "key": "field_5f15f9cb104ec",
            "label": "Spotlight Items",
            "name": "spotlight_items",
            "type": "repeater",
            "instructions": "",
            "required": 0,
            "conditional_logic": 0,
            "wrapper": {
                "width": "",
                "class": "",
                "id": ""
            },
            "collapsed": "field_5f15f9d4104ed",
            "min": 0,
            "max": 0,
            "layout": "table",
            "button_label": "",
            "sub_fields": [
                {
                    "key": "field_5f15f9d4104ed",
                    "label": "Contents",
                    "name": "contents",
                    "type": "textarea",
                    "instructions": "",
                    "required": 1,
                    "conditional_logic": 0,
                    "wrapper": {
                        "width": "",
                        "class": "",
                        "id": ""
                    },
                    "default_value": "",
                    "placeholder": "",
                    "maxlength": "",
                    "rows": "",
                    "new_lines": ""
                },
                {
                    "key": "field_5f15f9dd104ee",
                    "label": "Link",
                    "name": "link",
                    "type": "text",
                    "instructions": "",
                    "required": 0,
                    "conditional_logic": 0,
                    "wrapper": {
                        "width": "",
                        "class": "",
                        "id": ""
                    },
                    "default_value": "",
                    "placeholder": "",
                    "prepend": "",
                    "append": "",
                    "maxlength": ""
                },
                {
                    "key": "field_5f15f9e3104ef",
                    "label": "CTA",
                    "name": "cta",
                    "type": "text",
                    "instructions": "",
                    "required": 0,
                    "conditional_logic": 0,
                    "wrapper": {
                        "width": "",
                        "class": "",
                        "id": ""
                    },
                    "default_value": "",
                    "placeholder": "",
                    "prepend": "",
                    "append": "",
                    "maxlength": ""
                }
            ]
        },
        {
            "key": "field_56843ef5fbdc2",
            "label": "Copyright Footer",
            "name": "copyright",
            "type": "wysiwyg",
            "instructions": "",
            "required": 0,
            "conditional_logic": 0,
            "wrapper": {
                "width": "",
                "class": "",
                "id": ""
            },
            "default_value": "",
            "tabs": "all",
            "toolbar": "basic",
            "media_upload": 0,
            "delay": 0
        },
        {
            "key": "field_4046843ef5fbdc2",
            "label": "404 Message",
            "name": "404",
            "type": "wysiwyg",
            "instructions": "",
            "required": 0,
            "conditional_logic": 0,
            "wrapper": {
                "width": "",
                "class": "",
                "id": ""
            },
            "default_value": "",
            "tabs": "all",
            "toolbar": "full",
            "media_upload": 0,
            "delay": 0
        },
        {
            "key": "field_5abac7718a8cc",
            "label": "MSN Email Recipients",
            "name": "msn_email_recipients",
            "type": "repeater",
            "instructions": "",
            "required": 0,
            "conditional_logic": 0,
            "wrapper": {
                "width": "",
                "class": "",
                "id": ""
            },
            "collapsed": "",
            "min": 0,
            "max": 0,
            "layout": "table",
            "button_label": "",
            "sub_fields": [
                {
                    "key": "field_5abac7978a8cd",
                    "label": "Email Address",
                    "name": "email_address",
                    "type": "email",
                    "instructions": "",
                    "required": 0,
                    "conditional_logic": 0,
                    "wrapper": {
                        "width": "",
                        "class": "",
                        "id": ""
                    },
                    "default_value": "",
                    "placeholder": "",
                    "prepend": "",
                    "append": ""
                }
            ]
        },
        {
            "key": "field_5e8ef87099741",
            "label": "Social Media",
            "name": "",
            "type": "tab",
            "instructions": "",
            "required": 0,
            "conditional_logic": 0,
            "wrapper": {
                "width": "",
                "class": "",
                "id": ""
            },
            "placement": "top",
            "endpoint": 0
        },
        {
            "key": "field_593e5c9cd1caf",
            "label": "Twitter Handle",
            "name": "twitter_handle",
            "type": "text",
            "instructions": "Handle for Twitter sharing link.",
            "required": 0,
            "conditional_logic": 0,
            "wrapper": {
                "width": "",
                "class": "",
                "id": ""
            },
            "default_value": "iamwellandgood",
            "placeholder": "",
            "prepend": "@",
            "append": "",
            "maxlength": ""
        },
        {
            "key": "field_5683124535264",
            "label": "Instagram handle",
            "name": "instagram_handle",
            "type": "text",
            "instructions": "",
            "required": 0,
            "conditional_logic": 0,
            "wrapper": {
                "width": "",
                "class": "",
                "id": ""
            },
            "default_value": "wellgoodnyc",
            "placeholder": "",
            "prepend": "@",
            "append": "",
            "maxlength": ""
        },
        {
            "key": "field_56843797a173e",
            "label": "Social Media Links",
            "name": "social_media_links",
            "type": "repeater",
            "instructions": "",
            "required": 0,
            "conditional_logic": 0,
            "wrapper": {
                "width": "",
                "class": "",
                "id": ""
            },
            "collapsed": "field_568437efa173f",
            "min": 0,
            "max": 0,
            "layout": "table",
            "button_label": "Add Social Media Link",
            "sub_fields": [
                {
                    "key": "field_568437efa173f",
                    "label": "Label",
                    "name": "label",
                    "type": "text",
                    "instructions": "Name of social media link",
                    "required": 1,
                    "conditional_logic": 0,
                    "wrapper": {
                        "width": "",
                        "class": "",
                        "id": ""
                    },
                    "default_value": "",
                    "placeholder": "",
                    "prepend": "",
                    "append": "",
                    "maxlength": 100,
                    "readonly": 0,
                    "disabled": 0
                },
                {
                    "key": "field_56843806a1740",
                    "label": "Class",
                    "name": "class",
                    "type": "text",
                    "instructions": "Class name must match existing name in theme CSS",
                    "required": 1,
                    "conditional_logic": 0,
                    "wrapper": {
                        "width": "",
                        "class": "",
                        "id": ""
                    },
                    "default_value": "",
                    "placeholder": "",
                    "prepend": "",
                    "append": "",
                    "maxlength": "",
                    "readonly": 0,
                    "disabled": 0
                },
                {
                    "key": "field_56843839a1741",
                    "label": "URL",
                    "name": "url",
                    "type": "url",
                    "instructions": "",
                    "required": 1,
                    "conditional_logic": 0,
                    "wrapper": {
                        "width": "",
                        "class": "",
                        "id": ""
                    },
                    "default_value": "",
                    "placeholder": ""
                }
            ]
        },
        {
            "key": "field_5ed431a0ff69a",
            "label": "Instagram Auth API",
            "name": "instagram_auth",
            "type": "group",
            "instructions": "Instagram auth data to connect via API. Can be a different user from the main handle.",
            "required": 0,
            "conditional_logic": 0,
            "wrapper": {
                "width": "",
                "class": "",
                "id": ""
            },
            "layout": "block",
            "sub_fields": [
                {
                    "key": "field_5ed43215ff69b",
                    "label": "Username",
                    "name": "username",
                    "type": "text",
                    "instructions": "",
                    "required": 0,
                    "conditional_logic": 0,
                    "wrapper": {
                        "width": "50",
                        "class": "",
                        "id": ""
                    },
                    "default_value": "",
                    "placeholder": "",
                    "prepend": "@",
                    "append": "",
                    "maxlength": ""
                },
                {
                    "key": "field_5ed43243ff69c",
                    "label": "Password",
                    "name": "password",
                    "type": "password",
                    "instructions": "",
                    "required": 0,
                    "conditional_logic": 0,
                    "wrapper": {
                        "width": "50",
                        "class": "",
                        "id": ""
                    },
                    "placeholder": "",
                    "prepend": "",
                    "append": ""
                }
            ]
        },
        {
            "key": "field_59a77c6c13c7f",
            "label": "Council Hub",
            "name": "",
            "type": "tab",
            "instructions": "",
            "required": 0,
            "conditional_logic": 0,
            "wrapper": {
                "width": "",
                "class": "",
                "id": ""
            },
            "placement": "top",
            "endpoint": 0
        },
        {
            "key": "field_59b2bcbda4d0e",
            "label": "Mobile Menu Title",
            "name": "mobile_menu_title",
            "type": "text",
            "instructions": "CTA to be displayed for the council hub sub-nav on mobile devices",
            "required": 0,
            "conditional_logic": 0,
            "wrapper": {
                "width": "",
                "class": "",
                "id": ""
            },
            "default_value": "",
            "placeholder": "",
            "prepend": "",
            "append": "",
            "maxlength": ""
        },
        {
            "key": "field_59a782cc82234",
            "label": "Council Grid Title",
            "name": "council_grid_title",
            "type": "text",
            "instructions": "Title to be displayed above grid of council members.",
            "required": 0,
            "conditional_logic": 0,
            "wrapper": {
                "width": "",
                "class": "",
                "id": ""
            },
            "default_value": "",
            "placeholder": "",
            "prepend": "",
            "append": "",
            "maxlength": ""
        },
        {
            "key": "field_59a77d9cdd7a7",
            "label": "Council Members",
            "name": "council_members",
            "type": "flexible_content",
            "instructions": "",
            "required": 0,
            "conditional_logic": 0,
            "wrapper": {
                "width": "",
                "class": "",
                "id": ""
            },
            "button_label": "Add Member",
            "min": "",
            "max": "",
            "layouts": [
                {
                    "key": "59a77da69c859",
                    "name": "member",
                    "label": "Member",
                    "display": "block",
                    "sub_fields": [
                        {
                            "key": "field_59a77de4dd7a8",
                            "label": "Member Name",
                            "name": "member_name",
                            "type": "text",
                            "instructions": "",
                            "required": 0,
                            "conditional_logic": 0,
                            "wrapper": {
                                "width": "",
                                "class": "",
                                "id": ""
                            },
                            "default_value": "",
                            "placeholder": "",
                            "prepend": "",
                            "append": "",
                            "maxlength": ""
                        },
                        {
                            "key": "field_59a77dfbdd7a9",
                            "label": "Member Photo",
                            "name": "member_photo",
                            "type": "image",
                            "instructions": "Will be displayed in a circle. Minimum size 300x300",
                            "required": 0,
                            "conditional_logic": 0,
                            "wrapper": {
                                "width": "",
                                "class": "",
                                "id": ""
                            },
                            "return_format": "array",
                            "preview_size": "thumbnail",
                            "library": "all",
                            "min_width": 300,
                            "min_height": 300,
                            "min_size": "",
                            "max_width": "",
                            "max_height": "",
                            "max_size": "",
                            "mime_types": ""
                        },
                        {
                            "key": "field_59a77e41dd7aa",
                            "label": "Member Bio",
                            "name": "member_bio",
                            "type": "wysiwyg",
                            "instructions": "",
                            "required": 0,
                            "conditional_logic": 0,
                            "wrapper": {
                                "width": "",
                                "class": "",
                                "id": ""
                            },
                            "default_value": "",
                            "tabs": "all",
                            "toolbar": "full",
                            "media_upload": 1,
                            "delay": 0
                        },
                        {
                            "key": "field_59a77e53dd7ab",
                            "label": "Read More Link",
                            "name": "read_more_link",
                            "type": "url",
                            "instructions": "",
                            "required": 0,
                            "conditional_logic": 0,
                            "wrapper": {
                                "width": "50",
                                "class": "",
                                "id": ""
                            },
                            "default_value": "",
                            "placeholder": ""
                        },
                        {
                            "key": "field_59a77e83dd7ac",
                            "label": "Read More Label",
                            "name": "read_more_label",
                            "type": "text",
                            "instructions": "",
                            "required": 0,
                            "conditional_logic": 0,
                            "wrapper": {
                                "width": "50",
                                "class": "",
                                "id": ""
                            },
                            "default_value": "",
                            "placeholder": "",
                            "prepend": "",
                            "append": "",
                            "maxlength": ""
                        }
                    ],
                    "min": "",
                    "max": ""
                }
            ]
        },
        {
            "key": "field_5a67736cafde2",
            "label": "AMP Settings",
            "name": "",
            "type": "tab",
            "instructions": "",
            "required": 0,
            "conditional_logic": 0,
            "wrapper": {
                "width": "",
                "class": "",
                "id": ""
            },
            "placement": "top",
            "endpoint": 0
        },
        {
            "key": "field_5a70ccf60c599",
            "label": "GA Property Tracking Code",
            "name": "ga_property_tracking_code",
            "type": "text",
            "instructions": "Property ID for google analytics account. At time of implementation, this is used specifically for AMP Templates",
            "required": 0,
            "conditional_logic": 0,
            "wrapper": {
                "width": "",
                "class": "",
                "id": ""
            },
            "default_value": "",
            "placeholder": "",
            "prepend": "",
            "append": "",
            "maxlength": ""
        },
        {
            "key": "field_5a67739bafde3",
            "label": "Header Logo",
            "name": "amp_header_logo",
            "type": "image",
            "instructions": "The logo displayed at the top of the AMP Pages. Recommended height is no more than ~50px.",
            "required": 0,
            "conditional_logic": 0,
            "wrapper": {
                "width": "50",
                "class": "",
                "id": ""
            },
            "return_format": "array",
            "preview_size": "thumbnail",
            "library": "all",
            "min_width": "",
            "min_height": "",
            "min_size": "",
            "max_width": "",
            "max_height": "",
            "max_size": "",
            "mime_types": ""
        },
        {
            "key": "field_5a6776dad11ba",
            "label": "Logo Position",
            "name": "logo_position",
            "type": "select",
            "instructions": "Where the AMP logo is positioned in the header",
            "required": 0,
            "conditional_logic": 0,
            "wrapper": {
                "width": "50",
                "class": "",
                "id": ""
            },
            "choices": {
                "left": "Left",
                "center": "Center",
                "right": "Right"
            },
            "default_value": "center",
            "allow_null": 0,
            "multiple": 0,
            "ui": 0,
            "ajax": 0,
            "return_format": "value",
            "placeholder": ""
        },
        {
            "key": "field_5a677477afde6",
            "label": "Header Background Color",
            "name": "header_background_color",
            "type": "color_picker",
            "instructions": "",
            "required": 0,
            "conditional_logic": 0,
            "wrapper": {
                "width": "33",
                "class": "",
                "id": ""
            },
            "default_value": "#ffffff"
        },
        {
            "key": "field_5a677462afde5",
            "label": "Header Border Color",
            "name": "header_border_color",
            "type": "color_picker",
            "instructions": "",
            "required": 0,
            "conditional_logic": 0,
            "wrapper": {
                "width": "33",
                "class": "",
                "id": ""
            },
            "default_value": "#dd8979"
        },
        {
            "key": "field_5a67741bafde4",
            "label": "Link Color",
            "name": "link_color",
            "type": "color_picker",
            "instructions": "",
            "required": 0,
            "conditional_logic": 0,
            "wrapper": {
                "width": "33",
                "class": "",
                "id": ""
            },
            "default_value": "#dd8979"
        },
        {
            "key": "field_5eab521057cdc",
            "label": "Franchise Blurb",
            "name": "",
            "type": "tab",
            "instructions": "",
            "required": 0,
            "conditional_logic": 0,
            "wrapper": {
                "width": "",
                "class": "",
                "id": ""
            },
            "placement": "top",
            "endpoint": 0
        },
        {
            "key": "field_5eab521e57cdd",
            "label": "Globally Hide Franchise Blurb",
            "name": "hide_franchise_blurb",
            "type": "true_false",
            "instructions": "",
            "required": 0,
            "conditional_logic": 0,
            "wrapper": {
                "width": "",
                "class": "",
                "id": ""
            },
            "message": "",
            "default_value": 1,
            "ui": 1,
            "ui_on_text": "HIDE",
            "ui_off_text": "SHOW"
        },
        {
            "key": "field_5f15d9488690b",
            "label": "Partners",
            "name": "",
            "type": "tab",
            "instructions": "",
            "required": 0,
            "conditional_logic": 0,
            "wrapper": {
                "width": "",
                "class": "",
                "id": ""
            },
            "placement": "top",
            "endpoint": 0
        },
        {
            "key": "field_5f15d9528690c",
            "label": "Partnership Text",
            "name": "partnership_text",
            "type": "text",
            "instructions": "",
            "required": 0,
            "conditional_logic": 0,
            "wrapper": {
                "width": "",
                "class": "",
                "id": ""
            },
            "default_value": "Paid Content",
            "placeholder": "",
            "prepend": "",
            "append": "",
            "maxlength": ""
        },
        {
            "key": "field_5f61950e86db0",
            "label": "Hero Migration",
            "name": "",
            "type": "tab",
            "instructions": "",
            "required": 0,
            "conditional_logic": 0,
            "wrapper": {
                "width": "",
                "class": "",
                "id": ""
            },
            "placement": "top",
            "endpoint": 0
        },
        {
            "key": "field_5f61946486daf",
            "label": "Threshold Date",
            "name": "hero_migration_threshold_date",
            "type": "date_picker",
            "instructions": "Posts published after this Threshold Date will default to the \"Small Image\" Hero",
            "required": 0,
            "conditional_logic": 0,
            "wrapper": {
                "width": "",
                "class": "",
                "id": ""
            },
            "display_format": "F j, Y",
            "return_format": "Y-m-d",
            "first_day": 0
        }
    ],
    "location": [
        [
            {
                "param": "options_page",
                "operator": "==",
                "value": "theme-options"
            }
        ]
    ],
    "menu_order": 0,
    "position": "normal",
    "style": "seamless",
    "label_placement": "top",
    "instruction_placement": "label",
    "hide_on_screen": "",
    "active": 1,
    "description": "",
    "modified": 1600267927
}